datavolley/__init__.py
datavolley/analysis/__init__.py
datavolley/core/__init__.py
datavolley/core/attack_codes.py
datavolley/core/attack_combos.py
datavolley/core/code.py
datavolley/core/coordinates.py
datavolley/core/players.py
datavolley/core/plays.py
datavolley/core/set_calls.py
datavolley/core/teams.py
datavolley/core/vsm.py
datavolley/data/example_match.dvw
datavolley/io/__init__.py
datavolley/io/dvw.py
datavolley/io/plays.py
datavolley/utils/__init__.py
datavolley/utils/metadata.py
openvolley_pydatavolley-0.3.0.dist-info/METADATA
openvolley_pydatavolley-0.3.0.dist-info/WHEEL
openvolley_pydatavolley-0.3.0.dist-info/RECORD
