Metadata-Version: 2.4
Name: openvolley-pydatavolley
Version: 0.3.0
Summary: Extract data from DataVolley .dvw files and VolleyStation .vsm files
Project-URL: Homepage, https://github.com/openvolley/py-datavolley
Project-URL: Repository, https://github.com/openvolley/py-datavolley.git
Project-URL: Issues, https://github.com/openvolley/py-datavolley/issues
Author-email: Tyler Widdison <tylerperrywiddison@gmail.com>
Classifier: Development Status :: 3 - Alpha
Classifier: Intended Audience :: Developers
Classifier: License :: OSI Approved :: MIT License
Classifier: Programming Language :: Python :: 3.11
Classifier: Programming Language :: Python :: 3.12
Requires-Python: >=3.11
Requires-Dist: ruff>=0.14.9
Requires-Dist: ty>=0.0.1a34
